jjinline_files.py
jjinline_files-0.1.7.dist-info/LICENSE
jjinline_files-0.1.7.dist-info/WHEEL
jjinline_files-0.1.7.dist-info/METADATA
jjinline_files-0.1.7.dist-info/RECORD
