Metadata-Version: 2.1
Name: jjinline_files
Version: 0.1.7
Summary: jj Inline files - "not so pythonic" files inside your code
Keywords: config,inline files,templates,parser
Author-email: "J.João" <jj@di.uminho.pt>, Sofia Santos <sofiarsantos31@gmail.com>, TBarata <tiagobarata98@gmail.com>
Classifier: License :: OSI Approved :: MIT License
Requires-Dist: pyyaml >= 6.0
Requires-Dist: jinja2
Requires-Dist: pypugjs
Requires-Dist: pytest ; extra == "dev"
Project-URL: Home, https://github.com/...
Provides-Extra: dev
